odoo/addons/account_invoice_report_commercial_address/README.rst
odoo/addons/account_invoice_report_commercial_address/__init__.py
odoo/addons/account_invoice_report_commercial_address/__manifest__.py
odoo/addons/account_invoice_report_commercial_address/i18n/es.po
odoo/addons/account_invoice_report_commercial_address/models/__init__.py
odoo/addons/account_invoice_report_commercial_address/models/account_move.py
odoo/addons/account_invoice_report_commercial_address/readme/CONFIGURE.md
odoo/addons/account_invoice_report_commercial_address/readme/CONTRIBUTORS.md
odoo/addons/account_invoice_report_commercial_address/readme/DESCRIPTION.md
odoo/addons/account_invoice_report_commercial_address/readme/INSTALL.md
odoo/addons/account_invoice_report_commercial_address/readme/USAGE.md
odoo/addons/account_invoice_report_commercial_address/reports/report_invoice.xml
odoo/addons/account_invoice_report_commercial_address/static/description/icon.png
odoo/addons/account_invoice_report_commercial_address/static/description/index.html
odoo/addons/account_invoice_report_commercial_address/tests/__init__.py
odoo/addons/account_invoice_report_commercial_address/tests/test_account_invoice_report_commercial_address.py
odoo/addons/account_invoice_report_commercial_address/views/account_move_views.xml
odoo_addon_account_invoice_report_commercial_address-16.0.1.0.0.1.dist-info/METADATA
odoo_addon_account_invoice_report_commercial_address-16.0.1.0.0.1.dist-info/WHEEL
odoo_addon_account_invoice_report_commercial_address-16.0.1.0.0.1.dist-info/top_level.txt
odoo_addon_account_invoice_report_commercial_address-16.0.1.0.0.1.dist-info/RECORD
